Metadata-Version: 2.1
Name: entityidentity
Version: 0.0.2
Summary: Ontology / Entity Resolution
Home-page: https://github.com/petercotton/entityidentity
Author: Peter Cotton
Author-email: 
Classifier: Programming Language :: Python :: 3
Classifier: License :: OSI Approved :: MIT License
Classifier: Operating System :: OS Independent
Requires-Python: >=3.7
License-File: LICENSE
Requires-Dist: pandas>=1.3.0
Requires-Dist: rapidfuzz>=2.0.0
Requires-Dist: pyarrow>=10.0.0
Requires-Dist: requests>=2.25.0
Requires-Dist: tqdm>=4.0.0
Requires-Dist: pyyaml>=6.0.0
Provides-Extra: dev
Requires-Dist: pytest>=7.0.0; extra == "dev"
